setup.py
pyage/__init__.py
pyage/test_inject.py
pyage.egg-info/PKG-INFO
pyage.egg-info/SOURCES.txt
pyage.egg-info/dependency_links.txt
pyage.egg-info/requires.txt
pyage.egg-info/top_level.txt
pyage/conf/__init__.py
pyage/conf/emas_wojtek.py
pyage/conf/fagg_conf.py
pyage/conf/fconf.py
pyage/conf/femas_conf.py
pyage/conf/femas_single.py
pyage/conf/test_conf.py
pyage/core/__init__.py
pyage/core/address.py
pyage/core/bootstrap.py
pyage/core/emas.py
pyage/core/inject.py
pyage/core/locator.py
pyage/core/migration.py
pyage/core/operator.py
pyage/core/query.py
pyage/core/statistics.py
pyage/core/stop_condition.py
pyage/core/test_TorusLocator.py
pyage/core/workplace.py
pyage/core/agent/__init__.py
pyage/core/agent/agent.py
pyage/core/agent/aggregate.py
pyage/core/stats/__init__.py
pyage/core/stats/distributed.py
pyage/core/stats/emas_visualization.py
pyage/core/stats/gnuplot.py
pyage/solutions/__init__.py
pyage/solutions/evolution/__init__.py
pyage/solutions/evolution/crossover.py
pyage/solutions/evolution/evaluation.py
pyage/solutions/evolution/genotype.py
pyage/solutions/evolution/initializer.py
pyage/solutions/evolution/mutation.py
pyage/solutions/evolution/selection.py