Metadata-Version: 1.0
Name: pyage
Version: 1.2.12
Summary: Python Agent-based evolution
Home-page: UNKNOWN
Author: Maciej Kaziród
Author-email: kazirod.maciej@gmail.com
License: UNKNOWN
Platform: UNKNOWN
